hanzo_tools/__init__.py
hanzo_tools/reasoning/__init__.py
hanzo_tools/reasoning/critic_tool.py
hanzo_tools/reasoning/think_tool.py
hanzo_tools_reasoning-0.2.0.dist-info/METADATA
hanzo_tools_reasoning-0.2.0.dist-info/WHEEL
hanzo_tools_reasoning-0.2.0.dist-info/entry_points.txt
hanzo_tools_reasoning-0.2.0.dist-info/top_level.txt
hanzo_tools_reasoning-0.2.0.dist-info/RECORD
